dropbox_api_team_3/__init__.py
dropbox_api_team_3/box.py
dropbox_api_team_3/main.py
dropbox_api_team_3-0.1.1.dist-info/entry_points.txt
dropbox_api_team_3-0.1.1.dist-info/WHEEL
dropbox_api_team_3-0.1.1.dist-info/METADATA
dropbox_api_team_3-0.1.1.dist-info/RECORD
