Metadata-Version: 2.1
Name: dropbox-api-team-3
Version: 0.1.1
Summary: 
Author: Your Name
Author-email: you@example.com
Requires-Python: >=3.8,<4.0
Classifier: Programming Language :: Python :: 3
Classifier: Programming Language :: Python :: 3.8
Classifier: Programming Language :: Python :: 3.9
Requires-Dist: click (>=7.1.2,<8.0.0)
Requires-Dist: dropbox (>=11.7.0,<12.0.0)
Requires-Dist: pytest-mock (>=3.6.0,<4.0.0)
Requires-Dist: python-dotenv (>=0.17.1,<0.18.0)
